amalgam/__init__.py
amalgam/__main__.py
amalgam/amalgams.py
amalgam/cli.py
amalgam/engine.py
amalgam/environment.py
amalgam/grammar.lark
amalgam/parser.py
amalgam/primordials.py
amalgam_lisp-0.2.0.dist-info/entry_points.txt
amalgam_lisp-0.2.0.dist-info/LICENSE
amalgam_lisp-0.2.0.dist-info/WHEEL
amalgam_lisp-0.2.0.dist-info/METADATA
amalgam_lisp-0.2.0.dist-info/RECORD
