Metadata-Version: 2.1
Name: amalgam-lisp
Version: 0.2.0
Summary: Lisp-like interpreted language implemented in Python
Home-page: https://github.com/PureFunctor/amalgam-lisp
License: MIT
Author: PureFunctor
Author-email: purefunctor@gmail.com
Requires-Python: >=3.7,<4.0
Classifier: License :: OSI Approved :: MIT License
Classifier: Programming Language :: Python :: 3
Classifier: Programming Language :: Python :: 3.7
Classifier: Programming Language :: Python :: 3.8
Classifier: Programming Language :: Python :: 3.9
Requires-Dist: click (>=7.1.2,<8.0.0)
Requires-Dist: lark-parser (>=0.10.1,<0.11.0)
Requires-Dist: prompt-toolkit (>=3.0.7,<4.0.0)
Project-URL: Repository, https://github.com/PureFunctor/amalgam-lisp
